asyncutilsx/__init__.py
asyncutilsx-0.1.0.dist-info/licenses/NOTICE
asyncutilsx-0.1.0.dist-info/METADATA
asyncutilsx-0.1.0.dist-info/WHEEL
asyncutilsx-0.1.0.dist-info/top_level.txt
asyncutilsx-0.1.0.dist-info/RECORD
